[
  {
    "name": "KARAN",
    "email": "RAMAJII5050@GMAIL.COM",
    "message": "FDG",
    "submittedAt": "2026-07-01T19:15:26.262Z"
  },
  {
    "name": "KARAN",
    "email": "RAMAJII5050@GMAIL.COM",
    "message": "DFSGDH",
    "submittedAt": "2026-07-01T19:24:24.955Z"
  },
  {
    "name": "FHVN",
    "email": "JHAS4102@GMAIL.COM",
    "message": "GJHGJ",
    "submittedAt": "2026-07-01T19:37:17.630Z"
  },
  {
    "name": "jayanti jha",
    "phone": "8087909448",
    "email": "jhas4102@gmail.com",
    "message": "ebfvmwn",
    "submittedAt": "2026-07-05T13:05:15.999Z"
  }
]